typefast.py
typefast-1.0.1.dist-info/METADATA
typefast-1.0.1.dist-info/WHEEL
typefast-1.0.1.dist-info/entry_points.txt
typefast-1.0.1.dist-info/top_level.txt
typefast-1.0.1.dist-info/RECORD
