Metadata-Version: 2.4
Name: typefast
Version: 1.0.1
Summary: Terminal-based adaptive typing practice with progressive key learning
Home-page: https://github.com/seikixtc/typefast
Author: Will Isackson
Author-email: Will Isackson <seikixtc@gmail.com>
License: MIT
Project-URL: Homepage, https://github.com/seikixtc/typefast
Project-URL: Bug Reports, https://github.com/seikixtc/typefast/issues
Project-URL: Source, https://github.com/seikixtc/typefast
Project-URL: Documentation, https://github.com/seikixtc/typefast#readme
Keywords: typing,practice,tutor,keyboard,skills,learning,adaptive,terminal,cli
Classifier: Development Status :: 4 - Beta
Classifier: Environment :: Console
Classifier: Environment :: Console :: Curses
Classifier: Intended Audience :: End Users/Desktop
Classifier: Intended Audience :: Education
Classifier: License :: OSI Approved :: MIT License
Classifier: Natural Language :: English
Classifier: Operating System :: MacOS
Classifier: Operating System :: POSIX :: Linux
Classifier: Operating System :: Unix
Classifier: Programming Language :: Python :: 3
Classifier: Programming Language :: Python :: 3.6
Classifier: Programming Language :: Python :: 3.7
Classifier: Programming Language :: Python :: 3.8
Classifier: Programming Language :: Python :: 3.9
Classifier: Programming Language :: Python :: 3.10
Classifier: Programming Language :: Python :: 3.11
Classifier: Programming Language :: Python :: 3.12
Classifier: Topic :: Education
Classifier: Topic :: Games/Entertainment
Classifier: Topic :: Terminals
Requires-Python: >=3.6
Requires-Dist: asciichartpy>=1.5.25
Dynamic: author
Dynamic: home-page
Dynamic: requires-python
